LICENSE.txt
MANIFEST.in
README.md
setup.cfg
setup.py
bracketeer/__init__.py
bracketeer/slot_coordinates.py
bracketeer.egg-info/PKG-INFO
bracketeer.egg-info/SOURCES.txt
bracketeer.egg-info/dependency_links.txt
bracketeer.egg-info/requires.txt
bracketeer.egg-info/top_level.txt
bracketeer/empty_brackets/2017.jpg