Metadata-Version: 1.1
Name: bracketeer
Version: 0.1.9
Summary: Python Library for testing march madness brackets
Home-page: https://github.com/cshaley/bracketeer
Author: Charlie Haley
Author-email: charlie.haley@gmail.com
License: MIT
Download-URL: https://github.com/cshaley/bracketeer/archive/0.1.9.tar.gz
Platform: UNKNOWN
Classifier: Intended Audience :: Developers
Classifier: Intended Audience :: End Users/Desktop
Classifier: Intended Audience :: Information Technology
Classifier: License :: OSI Approved :: MIT License
Classifier: Operating System :: POSIX
Classifier: Operating System :: MacOS
Classifier: Operating System :: Unix
Classifier: Operating System :: Microsoft :: Windows
Classifier: Programming Language :: Python
Classifier: Programming Language :: Python :: 3.6
